{"stat.pickup.biomesoplenty.peach":2,"stat.cakeSlicesEaten":7,"stat.chestOpened":5,"stat.useItem.biomesoplenty.peach":2,"stat.drop.minecraft.wooden_pickaxe":2,"stat.pickup.minecraft.gravel":10,"stat.useItem.minecraft.glass_bottle":32,"stat.mineBlock.minecraft.cobblestone":3,"stat.pickup.minecraft.stone_axe":1,"stat.pickup.minecraft.flint":1,"stat.mineBlock.toughasnails.campfire":1,"stat.useItem.minecraft.potion":33,"stat.craftItem.biomesoplenty.planks_0":160,"stat.swimOneCm":7349,"stat.jump":573,"stat.climbOneCm":628,"stat.fallOneCm":12045,"stat.pickup.minecraft.iron_ingot":1,"stat.drop.minecraft.cobblestone":1,"stat.pickup.minecraft.carrot":46,"stat.useItem.minecraft.stone_axe":31,"stat.crouchOneCm":360,"stat.craftItem.minecraft.chest":1,"stat.useItem.minecraft.stone_slab2":18,"stat.drop.minecraft.glass":1,"stat.craftingTableInteraction":17,"stat.pickup.minecraft.rotten_flesh":8,"stat.pickup.minecraft.sand":33,"stat.craftItem.minecraft.furnace":2,"stat.craftItem.minecraft.flint_and_steel":1,"stat.pickup.minecraft.iron_axe":1,"stat.mineBlock.minecraft.glass_pane":2,"stat.pickup.minecraft.wooden_pickaxe":1,"stat.damageTaken":275,"stat.mineBlock.minecraft.torch":18,"stat.craftItem.minecraft.stone_pickaxe":1,"stat.useItem.minecraft.wooden_pickaxe":16,"stat.pickup.minecraft.cobblestone":98,"stat.useItem.minecraft.stone_shovel":12,"stat.craftItem.minecraft.stone_sword":1,"stat.flyOneCm":106535,"stat.pickup.minecraft.bed":1,"stat.pickup.minecraft.wheat_seeds":72,"stat.pickup.minecraft.brown_mushroom":1,"stat.mineBlock.minecraft.sand":33,"stat.pickup.minecraft.potato":45,"stat.pickup.minecraft.rabbit_hide":3,"stat.craftItem.toughasnails.campfire":2,"stat.drop.minecraft.sand":1,"stat.mineBlock.minecraft.gravel":11,"stat.useItem.minecraft.stone_pickaxe":81,"stat.craftItem.minecraft.glass":1,"stat.damageDealt":790,"stat.killEntity.Rabbit":3,"stat.timeSinceDeath":34487,"stat.craftItem.minecraft.baked_potato":25,"stat.craftItem.spartanshields.shield_basic_wood":1,"stat.craftItem.minecraft.wooden_pickaxe":1,"stat.mineBlock.biomesoplenty.log_3":47,"stat.craftItem.minecraft.stone_shovel":1,"stat.walkOneCm":89956,"stat.useItem.minecraft.torch":13,"stat.useItem.minecraft.potato":1,"stat.mineBlock.biomesoplenty.leaves_5":251,"stat.pickup.minecraft.crafting_table":1,"stat.useItem.minecraft.cobblestone":20,"stat.craftItem.minecraft.crafting_table":2,"stat.furnaceInteraction":22,"stat.pickup.biomesoplenty.sapling_2":6,"stat.useItem.minecraft.gravel":2,"stat.mineBlock.minecraft.double_plant":1,"stat.pickup.srparasites.lurecomponent1":4,"stat.pickup.minecraft.log":10,"stat.craftItem.minecraft.stone_slab2":0,"stat.pickup.minecraft.sapling":3,"stat.sprintOneCm":83173,"stat.craftItem.minecraft.stick":8,"stat.pickup.biomesoplenty.log_3":40,"stat.craftItem.minecraft.planks":8,"stat.pickup.minecraft.potion":1,"stat.useItem.biomesoplenty.planks_0":1,"stat.mineBlock.minecraft.crafting_table":1,"stat.useItem.minecraft.carrot":2,"stat.mobKills":9,"stat.mineBlock.minecraft.log":10,"stat.drop":5,"stat.mineBlock.minecraft.leaves":107,"stat.playOneMinute":34487,"stat.craftItem.spartanshields.shield_basic_stone":1,"stat.pickup.minecraft.torch":19,"stat.sneakTime":829,"stat.pickup.minecraft.rabbit":2,"stat.pickup.minecraft.item_frame":1,"stat.killEntity.Zombie":2,"stat.mineBlock.minecraft.stone":93,"stat.mineBlock.minecraft.tallgrass":4,"stat.diveOneCm":21985,"stat.pickup.minecraft.wheat":10}